graf/__init__.py
graf/client.py
graf/singleton.py
graf_py-0.1.1.dist-info/DESCRIPTION.rst
graf_py-0.1.1.dist-info/METADATA
graf_py-0.1.1.dist-info/RECORD
graf_py-0.1.1.dist-info/WHEEL
graf_py-0.1.1.dist-info/metadata.json
graf_py-0.1.1.dist-info/top_level.txt
