Metadata-Version: 2.0
Name: graf-py
Version: 0.1.1
Summary: Graf Python Client
Home-page: http://github.com/iograf/graf-py
Author: Victor Gama
Author-email: hey@vito.io
License: MIT
Keywords: graf iograf metrics events
Platform: UNKNOWN
Classifier: Development Status :: 4 - Beta
Classifier: License :: OSI Approved :: MIT License
Classifier: Programming Language :: Python :: 2.7
Classifier: Programming Language :: Python :: 3
Classifier: Topic :: Text Processing :: Linguistic
Classifier: Topic :: System :: Logging
Classifier: Topic :: System :: Monitoring
Classifier: Topic :: Software Development :: Quality Assurance
